pysymmpol/__init__.py
pysymmpol/partitions/__init__.py
pysymmpol/partitions/conjugacy.py
pysymmpol/partitions/states.py
pysymmpol/partitions/young.py
pysymmpol/polynomials/__init__.py
pysymmpol/polynomials/elementary.py
pysymmpol/polynomials/hall.py
pysymmpol/polynomials/homogeneous.py
pysymmpol/polynomials/monomial.py
pysymmpol/polynomials/schur.py
pysymmpol/py.typed
pysymmpol/utils/__init__.py
pysymmpol/utils/inner.py
pysymmpol/utils/tools.py
pysymmpol-0.1.2.dist-info/LICENSE
pysymmpol-0.1.2.dist-info/METADATA
pysymmpol-0.1.2.dist-info/WHEEL
pysymmpol-0.1.2.dist-info/RECORD
