Metadata-Version: 2.1
Name: pysymmpol
Version: 0.1.2
Summary: A python package for manipulation of symmetric polynomials.
License: GPL-3.0
Author: Thiago Araujo
Requires-Python: >=3.12,<4.0
Classifier: License :: OSI Approved :: GNU General Public License v3 (GPLv3)
Classifier: Programming Language :: Python :: 3
Classifier: Programming Language :: Python :: 3.12
Requires-Dist: numpy (>=1.26.4,<2.0.0)
Requires-Dist: sympy (>=1.12,<2.0)
